wltk/__init__.py
wltk/parser.py
wltk-0.1.0.dist-info/licenses/LICENSE
wltk-0.1.0.dist-info/METADATA
wltk-0.1.0.dist-info/WHEEL
wltk-0.1.0.dist-info/top_level.txt
wltk-0.1.0.dist-info/RECORD
