Metadata-Version: 2.4
Name: wltk
Version: 0.1.0
Summary: WLTK is a toolkit for parsing and analyzing web server logs. Designed to help developers and analysts extract insights from access logs, monitor traffic patterns, or detect anomalies with ease.
Author-email: Mahendra Data <data.nduth@gmail.com>
License:                                  Apache License
Project-URL: Homepage, https://github.com/mahendradata/weblog-toolkit
Requires-Python: >=3.11
License-File: LICENSE
Requires-Dist: pandas
Dynamic: license-file
